printdescribe/__init__.py
printdescribe/printdesc.py
printdescribe-0.2.2.1.dist-info/METADATA
printdescribe-0.2.2.1.dist-info/WHEEL
printdescribe-0.2.2.1.dist-info/top_level.txt
printdescribe-0.2.2.1.dist-info/RECORD
